LICENSE
MANIFEST.in
README.md
setup.cfg
setup.py
openimu/__init__.py
openimu/__main__.py
openimu/bootloader_input_packet.py
openimu/commands.py
openimu/connection.json
openimu/file_storage.py
openimu/global_vars.py
openimu/imu_input_packet.py
openimu/openimu.json
openimu/openimu.py
openimu/server.py
openimu_test10.egg-info/PKG-INFO
openimu_test10.egg-info/SOURCES.txt
openimu_test10.egg-info/dependency_links.txt
openimu_test10.egg-info/entry_points.txt
openimu_test10.egg-info/requires.txt
openimu_test10.egg-info/top_level.txt